toolconfig/__init__.py
toolconfig/crud.py
toolconfig/exceptions.py
toolconfig/filesystem.py
toolconfig/py.typed
toolconfig/spec.py
toolconfig/validation.py
toolconf-0.1.2.dist-info/LICENSE
toolconf-0.1.2.dist-info/WHEEL
toolconf-0.1.2.dist-info/METADATA
toolconf-0.1.2.dist-info/RECORD
