Metadata-Version: 2.1
Name: toolconf
Version: 0.1.2
Summary: toolconfig provides tools for loading and managing config files
Requires-Python: >=3.7
Requires-Dist: typing_extensions>=4.0.0
Requires-Dist: pyyaml ; extra == "yaml"
Provides-Extra: yaml
